gestureflow/__init__.py
gestureflow/definitions.py
gestureflow/sample_gesture_trackers.py
gestureflow/sample_runners.py
gestureflow/sample_state_trackers.py
gestureflow/settings.py
gestureflow/tracker.py
gestureflow-0.0.4.dist-info/METADATA
gestureflow-0.0.4.dist-info/WHEEL
gestureflow-0.0.4.dist-info/top_level.txt
gestureflow-0.0.4.dist-info/RECORD
